pytest_annotate/__init__.py
pytest_annotate/plugin.py
pytest_annotate-1.0.5.dist-info/AUTHORS.md
pytest_annotate-1.0.5.dist-info/LICENSE.txt
pytest_annotate-1.0.5.dist-info/METADATA
pytest_annotate-1.0.5.dist-info/WHEEL
pytest_annotate-1.0.5.dist-info/entry_points.txt
pytest_annotate-1.0.5.dist-info/top_level.txt
pytest_annotate-1.0.5.dist-info/RECORD
